nqdm/__init__.py
nqdm-0.4.12.dist-info/LICENSE
nqdm-0.4.12.dist-info/METADATA
nqdm-0.4.12.dist-info/WHEEL
nqdm-0.4.12.dist-info/top_level.txt
nqdm-0.4.12.dist-info/RECORD
