Metadata-Version: 2.1
Name: nqdm
Version: 0.4.12
Summary: NQDM -- An extension of TQDM which enables you to loop over multiple objects simultaneously, and specify the depth of iteration for each object. It is just pure Python magic, no extra libraries needed. It is customizable, minimal and open source.
Home-page: https://github.com/yamaceay/nqdm
Author: Yamac Eren Ay
Author-email: yamacerenay2001@gmail.com
License: UNKNOWN
Platform: UNKNOWN
Classifier: Programming Language :: Python :: 3
Classifier: License :: OSI Approved :: MIT License
Classifier: Operating System :: OS Independent
Requires-Python: >=3.8
Requires-Dist: numpy (==1.22.4)
Requires-Dist: setuptools (==49.2.1)
Requires-Dist: tqdm (==4.60.0)
